inception_reports/__init__.py
inception_reports/__main__.py
inception_reports/dashboard_version.py
inception_reports/generate_reports_lead.py
inception_reports/generate_reports_manager.py
inception_reports/config/logging_config.yaml
inception_reports/data/document_types.json
inception_reports/data/excluded_types.json
inception_reports/data/specialties.json
inception_reports-0.9.7.dist-info/licenses/LICENSE
inception_reports-0.9.7.dist-info/licenses/NOTICE.txt
inception_reports-0.9.7.dist-info/METADATA
inception_reports-0.9.7.dist-info/WHEEL
inception_reports-0.9.7.dist-info/entry_points.txt
inception_reports-0.9.7.dist-info/top_level.txt
inception_reports-0.9.7.dist-info/RECORD
