Metadata-Version: 2.4
Name: inception_reports
Version: 0.9.7
Summary: Generate plots that report the progress of an INCEpTION project.
Author-email: Serwar <serwar.basch@tu-darmstadt.de>
Project-URL: Homepage, https://github.com/inception-project/inception-reporting-dashboard
Classifier: Programming Language :: Python :: 3
Classifier: License :: OSI Approved :: Apache Software License
Classifier: Operating System :: OS Independent
Requires-Python: >=3.11
License-File: LICENSE
License-File: NOTICE.txt
Requires-Dist: streamlit
Requires-Dist: pandas
Requires-Dist: plotly
Requires-Dist: numpy
Requires-Dist: dkpro-cassis
Requires-Dist: pycaprio
Requires-Dist: PyYAML
Requires-Dist: rdflib
Dynamic: license-file
